zthreading/__init__.py
zthreading/decorators.py
zthreading/decorators_test.py
zthreading/events.py
zthreading/events_test.py
zthreading/exceptions.py
zthreading/signals.py
zthreading/signals_term_tester.py
zthreading/signals_test.py
zthreading/tasks.py
zthreading/tasks_test.py
zthreading/thread_queue.py
zthreading/thread_queue_test.py
zthreading-0.1.16.dist-info/METADATA
zthreading-0.1.16.dist-info/WHEEL
zthreading-0.1.16.dist-info/top_level.txt
zthreading-0.1.16.dist-info/RECORD
